FullAdder.v
module Adder(a,b,cIn,s,cOut);
	input [3:0] a, b;
	output [3:0] s;
	input cIn; 
	output cOut;
	wire cOut1, cOut2, cOut3;

	FullAdder fa0(a[0],b[0],cIn,s[0],cOut1);
	FullAdder fa1(a[1],b[1],cOut1,s[1],cOut2);
	FullAdder fa2(a[2],b[2],cOut2,s[2],cOut3);
	FullAdder fa3(a[3],b[3],cOut3,s[3],cOut);

endmodule


module FullAdder(a,b,cIn,s,cOut);
	input a,b,cIn; 
	output s,cOut;
	assign {cOut,s} = a + b + cIn;
endmodule


module testbench;
	reg [3:0] a, b;
	wire [3:0] s;
	wire cOut;
	reg [3:0] i,j;

	Adder myFullAdder(a,b,1'b0,s,cOut);
	initial 
	begin
		a <= 4'b0000;
		b <= 4'b0000;

		$dumpfile("adder.vcd"); 
		$dumpvars(0, myFullAdder);
     
		for(i=0; i<15; i=i+1) 
		begin
			#5 $display(" a(0000)   b(0000)   s(0000)  cOut\n");

			for(j=0; j<15; j=j+1) 
			begin
				a <= i;
 				b <= j;
				#5 $display("%2d(%b)  %2d(%b)  %2d(%b)   %b", i, i, j, j, s, s, cOut);
	  		end
			#5 $display("\n");
  		end
		#10 $finish;
	end
endmodule

adder.vcd
$date
	Mon May 28 19:12:28 2018
$end
$version
	Icarus Verilog
$end
$timescale
	1s
$end
$scope module testbench $end
$scope module myFullAdder $end
$var wire 4 ! a [3:0] $end
$var wire 4 " b [3:0] $end
$var wire 1 # cIn $end
$var wire 1 $ cOut $end
$var wire 1 % cOut1 $end
$var wire 1 & cOut2 $end
$var wire 1 ' cOut3 $end
$var wire 4 ( s [3:0] $end
$scope module fa0 $end
$var wire 1 ) a $end
$var wire 1 * b $end
$var wire 1 # cIn $end
$var wire 1 % cOut $end
$var wire 1 + s $end
$upscope $end
$scope module fa1 $end
$var wire 1 , a $end
$var wire 1 - b $end
$var wire 1 % cIn $end
$var wire 1 & cOut $end
$var wire 1 . s $end
$upscope $end
$scope module fa2 $end
$var wire 1 / a $end
$var wire 1 0 b $end
$var wire 1 & cIn $end
$var wire 1 ' cOut $end
$var wire 1 1 s $end
$upscope $end
$scope module fa3 $end
$var wire 1 2 a $end
$var wire 1 3 b $end
$var wire 1 ' cIn $end
$var wire 1 $ cOut $end
$var wire 1 4 s $end
$upscope $end
$upscope $end
$upscope $end
$enddefinitions $end
#0
$dumpvars
04
03
02
01
00
0/
0.
0-
0,
0+
0*
0)
b0 (
0'
0&
0%
0$
0#
b0 "
b0 !
$end
#10
1+
b1 (
1*
b1 "
#15
0+
1.
b10 (
0*
1-
b10 "
#20
1+
b11 (
1*
b11 "
#25
0+
0.
11
b100 (
0*
0-
10
b100 "
#30
1+
b101 (
1*
b101 "
#35
0+
1.
b110 (
0*
1-
b110 "
#40
1+
b111 (
1*
b111 "
#45
0+
0.
01
14
b1000 (
0*
0-
00
13
b1000 "
#50
1+
b1001 (
1*
b1001 "
#55
0+
1.
b1010 (
0*
1-
b1010 "
#60
1+
b1011 (
1*
b1011 "
#65
0+
0.
11
b1100 (
0*
0-
10
b1100 "
#70
1+
b1101 (
1*
b1101 "
#75
0+
1.
b1110 (
0*
1-
b1110 "
#90
0.
01
04
1+
b1 (
0-
00
03
1)
b0 "
b1 !
#95
1.
0+
b10 (
1%
1*
b1 "
#100
01
1+
0%
1.
b11 (
0&
0*
1-
b10 "
#105
11
0.
1&
0+
b100 (
1%
1*
b11 "
#110
04
1+
0%
0.
0&
11
b101 (
0'
0*
0-
10
b100 "
#115
1.
0+
b110 (
1%
1*
b101 "
#120
04
11
0'
1+
0%
1.
b111 (
0&
0*
1-
b110 "
#125
14
01
1'
0.
1&
0+
b1000 (
1%
1*
b111 "
#130
1+
0%
0.
0&
01
0'
14
b1001 (
0$
0*
0-
00
13
b1000 "
#135
1.
0+
b1010 (
1%
1*
b1001 "
#140
01
1+
0%
1.
b1011 (
0&
0*
1-
b1010 "
#145
11
0.
1&
0+
b1100 (
1%
1*
b1011 "
#150
14
0$
1+
0%
0.
0&
11
b1101 (
0'
0*
0-
10
b1100 "
#155
1.
0+
b1110 (
1%
1*
b1101 "
#160
14
0$
11
0'
1+
0%
1.
b1111 (
0&
0*
1-
b1110 "
#175
01
04
0+
b10 (
0-
00
03
0)
1,
b0 "
b10 !
#180
1+
b11 (
1*
b1 "
#185
11
0+
0.
b100 (
1&
0*
1-
b10 "
#190
1+
b101 (
1*
b11 "
#195
04
0+
1.
0&
11
b110 (
0'
0*
0-
10
b100 "
#200
1+
b111 (
1*
b101 "
#205
14
01
1'
0+
0.
b1000 (
1&
0*
1-
b110 "
#210
1+
b1001 (
1*
b111 "
#215
0+
1.
0&
01
0'
14
b1010 (
0$
0*
0-
00
13
b1000 "
#220
1+
b1011 (
1*
b1001 "
#225
11
0+
0.
b1100 (
1&
0*
1-
b1010 "
#230
1+
b1101 (
1*
b1011 "
#235
14
0$
0+
1.
0&
11
b1110 (
0'
0*
0-
10
b1100 "
#240
1+
b1111 (
1*
b1101 "
#245
04
1$
01
1'
0+
0.
b0 (
1&
0*
1-
b1110 "
#260
1.
0&
01
0'
04
0$
1+
b11 (
0-
00
03
1)
b0 "
b11 !
#265
11
0.
1&
0+
b100 (
1%
1*
b1 "
#270
1+
0%
0.
b101 (
0*
1-
b10 "
#275
1.
0+
b110 (
1%
1*
b11 "
#280
0&
04
1+
0%
1.
11
b111 (
0'
0*
0-
10
b100 "
#285
14
01
1'
0.
1&
0+
b1000 (
1%
1*
b101 "
#290
1+
0%
0.
b1001 (
0*
1-
b110 "
#295
1.
0+
b1010 (
1%
1*
b111 "
#300
0&
1+
0%
1.
01
0'
14
b1011 (
0$
0*
0-
00
13
b1000 "
#305
11
0.
1&
0+
b1100 (
1%
1*
b1001 "
#310
1+
0%
0.
b1101 (
0*
1-
b1010 "
#315
1.
0+
b1110 (
1%
1*
b1011 "
#320
0&
14
0$
1+
0%
1.
11
b1111 (
0'
0*
0-
10
b1100 "
#325
04
1$
01
1'
0.
1&
0+
b0 (
1%
1*
b1101 "
#330
1+
0%
0.
b1 (
0*
1-
b1110 "
#345
11
0'
04
0$
0+
b100 (
0&
0-
00
03
0)
0,
1/
b0 "
b100 !
#350
1+
b101 (
1*
b1 "
#355
0+
1.
b110 (
0*
1-
b10 "
#360
1+
b111 (
1*
b11 "
#365
14
0+
0.
01
b1000 (
1'
0*
0-
10
b100 "
#370
1+
b1001 (
1*
b101 "
#375
0+
1.
b1010 (
0*
1-
b110 "
#380
1+
b1011 (
1*
b111 "
#385
0+
0.
11
0'
14
b1100 (
0$
0*
0-
00
13
b1000 "
#390
1+
b1101 (
1*
b1001 "
#395
0+
1.
b1110 (
0*
1-
b1010 "
#400
1+
b1111 (
1*
b1011 "
#405
04
1$
0+
0.
01
b0 (
1'
0*
0-
10
b1100 "
#410
1+
b1 (
1*
b1101 "
#415
0+
1.
b10 (
0*
1-
b1110 "
#430
0.
11
0'
04
0$
1+
b101 (
0-
00
03
1)
b0 "
b101 !
#435
1.
0+
b110 (
1%
1*
b1 "
#440
04
11
0'
1+
0%
1.
b111 (
0&
0*
1-
b10 "
#445
14
01
1'
0.
1&
0+
b1000 (
1%
1*
b11 "
#450
1+
0%
0.
0&
01
b1001 (
0*
0-
10
b100 "
#455
1.
0+
b1010 (
1%
1*
b101 "
#460
01
1+
0%
1.
b1011 (
0&
0*
1-
b110 "
#465
11
0.
1&
0+
b1100 (
1%
1*
b111 "
#470
0'
1+
0%
0.
0&
11
14
b1101 (
0$
0*
0-
00
13
b1000 "
#475
1.
0+
b1110 (
1%
1*
b1001 "
#480
14
0$
11
0'
1+
0%
1.
b1111 (
0&
0*
1-
b1010 "
#485
04
1$
01
1'
0.
1&
0+
b0 (
1%
1*
b1011 "
#490
1+
0%
0.
0&
01
b1 (
0*
0-
10
b1100 "
#495
1.
0+
b10 (
1%
1*
b1101 "
#500
01
1+
0%
1.
b11 (
0&
0*
1-
b1110 "
#515
11
0'
04
0$
0+
b110 (
0-
00
03
0)
1,
b0 "
b110 !
#520
1+
b111 (
1*
b1 "
#525
14
01
1'
0+
0.
b1000 (
1&
0*
1-
b10 "
#530
1+
b1001 (
1*
b11 "
#535
0+
1.
0&
01
b1010 (
0*
0-
10
b100 "
#540
1+
b1011 (
1*
b101 "
#545
11
0+
0.
b1100 (
1&
0*
1-
b110 "
#550
1+
b1101 (
1*
b111 "
#555
0'
0+
1.
0&
11
14
b1110 (
0$
0*
0-
00
13
b1000 "
#560
1+
b1111 (
1*
b1001 "
#565
04
1$
01
1'
0+
0.
b0 (
1&
0*
1-
b1010 "
#570
1+
b1 (
1*
b1011 "
#575
0+
1.
0&
01
b10 (
0*
0-
10
b1100 "
#580
1+
b11 (
1*
b1101 "
#585
11
0+
0.
b100 (
1&
0*
1-
b1110 "
#600
0'
1.
0&
11
04
0$
1+
b111 (
0-
00
03
1)
b0 "
b111 !
#605
14
01
1'
0.
1&
0+
b1000 (
1%
1*
b1 "
#610
1+
0%
0.
b1001 (
0*
1-
b10 "
#615
1.
0+
b1010 (
1%
1*
b11 "
#620
0&
1+
0%
1.
01
b1011 (
0*
0-
10
b100 "
#625
11
0.
1&
0+
b1100 (
1%
1*
b101 "
#630
1+
0%
0.
b1101 (
0*
1-
b110 "
#635
1.
0+
b1110 (
1%
1*
b111 "
#640
0'
0&
1+
0%
1.
11
14
b1111 (
0$
0*
0-
00
13
b1000 "
#645
04
1$
01
1'
0.
1&
0+
b0 (
1%
1*
b1001 "
#650
1+
0%
0.
b1 (
0*
1-
b1010 "
#655
1.
0+
b10 (
1%
1*
b1011 "
#660
0&
1+
0%
1.
01
b11 (
0*
0-
10
b1100 "
#665
11
0.
1&
0+
b100 (
1%
1*
b1101 "
#670
1+
0%
0.
b101 (
0*
1-
b1110 "
#685
14
0$
01
0'
0+
b1000 (
0&
0-
00
03
0)
0,
0/
12
b0 "
b1000 !
#690
1+
b1001 (
1*
b1 "
#695
0+
1.
b1010 (
0*
1-
b10 "
#700
1+
b1011 (
1*
b11 "
#705
0+
0.
11
b1100 (
0*
0-
10
b100 "
#710
1+
b1101 (
1*
b101 "
#715
0+
1.
b1110 (
0*
1-
b110 "
#720
1+
b1111 (
1*
b111 "
#725
0+
0.
01
04
b0 (
1$
0*
0-
00
13
b1000 "
#730
1+
b1 (
1*
b1001 "
#735
0+
1.
b10 (
0*
1-
b1010 "
#740
1+
b11 (
1*
b1011 "
#745
0+
0.
11
b100 (
0*
0-
10
b1100 "
#750
1+
b101 (
1*
b1101 "
#755
0+
1.
b110 (
0*
1-
b1110 "
#770
0.
01
14
0$
1+
b1001 (
0-
00
03
1)
b0 "
b1001 !
#775
1.
0+
b1010 (
1%
1*
b1 "
#780
01
1+
0%
1.
b1011 (
0&
0*
1-
b10 "
#785
11
0.
1&
0+
b1100 (
1%
1*
b11 "
#790
14
0$
1+
0%
0.
0&
11
b1101 (
0'
0*
0-
10
b100 "
#795
1.
0+
b1110 (
1%
1*
b101 "
#800
14
0$
11
0'
1+
0%
1.
b1111 (
0&
0*
1-
b110 "
#805
04
1$
01
1'
0.
1&
0+
b0 (
1%
1*
b111 "
#810
1+
0%
0.
0&
01
0'
04
b1 (
0*
0-
00
13
b1000 "
#815
1.
0+
b10 (
1%
1*
b1001 "
#820
01
1+
0%
1.
b11 (
0&
0*
1-
b1010 "
#825
11
0.
1&
0+
b100 (
1%
1*
b1011 "
#830
04
1+
0%
0.
0&
11
b101 (
0'
0*
0-
10
b1100 "
#835
1.
0+
b110 (
1%
1*
b1101 "
#840
04
11
0'
1+
0%
1.
b111 (
0&
0*
1-
b1110 "
#855
01
14
0$
0+
b1010 (
0-
00
03
0)
1,
b0 "
b1010 !
#860
1+
b1011 (
1*
b1 "
#865
11
0+
0.
b1100 (
1&
0*
1-
b10 "
#870
1+
b1101 (
1*
b11 "
#875
14
0$
0+
1.
0&
11
b1110 (
0'
0*
0-
10
b100 "
#880
1+
b1111 (
1*
b101 "
#885
04
1$
01
1'
0+
0.
b0 (
1&
0*
1-
b110 "
#890
1+
b1 (
1*
b111 "
#895
0+
1.
0&
01
0'
04
b10 (
0*
0-
00
13
b1000 "
#900
1+
b11 (
1*
b1001 "
#905
11
0+
0.
b100 (
1&
0*
1-
b1010 "
#910
1+
b101 (
1*
b1011 "
#915
04
0+
1.
0&
11
b110 (
0'
0*
0-
10
b1100 "
#920
1+
b111 (
1*
b1101 "
#925
14
01
1'
0+
0.
b1000 (
1&
0*
1-
b1110 "
#940
0$
1.
0&
01
0'
14
1+
b1011 (
0-
00
03
1)
b0 "
b1011 !
#945
11
0.
1&
0+
b1100 (
1%
1*
b1 "
#950
1+
0%
0.
b1101 (
0*
1-
b10 "
#955
1.
0+
b1110 (
1%
1*
b11 "
#960
0&
14
0$
1+
0%
1.
11
b1111 (
0'
0*
0-
10
b100 "
#965
04
1$
01
1'
0.
1&
0+
b0 (
1%
1*
b101 "
#970
1+
0%
0.
b1 (
0*
1-
b110 "
#975
1.
0+
b10 (
1%
1*
b111 "
#980
0&
1+
0%
1.
01
0'
04
b11 (
0*
0-
00
13
b1000 "
#985
11
0.
1&
0+
b100 (
1%
1*
b1001 "
#990
1+
0%
0.
b101 (
0*
1-
b1010 "
#995
1.
0+
b110 (
1%
1*
b1011 "
#1000
0&
04
1+
0%
1.
11
b111 (
0'
0*
0-
10
b1100 "
#1005
14
01
1'
0.
1&
0+
b1000 (
1%
1*
b1101 "
#1010
1+
0%
0.
b1001 (
0*
1-
b1110 "
#1025
0$
11
0'
14
0+
b1100 (
0&
0-
00
03
0)
0,
1/
b0 "
b1100 !
#1030
1+
b1101 (
1*
b1 "
#1035
0+
1.
b1110 (
0*
1-
b10 "
#1040
1+
b1111 (
1*
b11 "
#1045
04
1$
0+
0.
01
b0 (
1'
0*
0-
10
b100 "
#1050
1+
b1 (
1*
b101 "
#1055
0+
1.
b10 (
0*
1-
b110 "
#1060
1+
b11 (
1*
b111 "
#1065
0+
0.
11
0'
04
b100 (
0*
0-
00
13
b1000 "
#1070
1+
b101 (
1*
b1001 "
#1075
0+
1.
b110 (
0*
1-
b1010 "
#1080
1+
b111 (
1*
b1011 "
#1085
14
0+
0.
01
b1000 (
1'
0*
0-
10
b1100 "
#1090
1+
b1001 (
1*
b1101 "
#1095
0+
1.
b1010 (
0*
1-
b1110 "
#1110
0$
0.
11
0'
14
1+
b1101 (
0-
00
03
1)
b0 "
b1101 !
#1115
1.
0+
b1110 (
1%
1*
b1 "
#1120
14
0$
11
0'
1+
0%
1.
b1111 (
0&
0*
1-
b10 "
#1125
04
1$
01
1'
0.
1&
0+
b0 (
1%
1*
b11 "
#1130
1+
0%
0.
0&
01
b1 (
0*
0-
10
b100 "
#1135
1.
0+
b10 (
1%
1*
b101 "
#1140
01
1+
0%
1.
b11 (
0&
0*
1-
b110 "
#1145
11
0.
1&
0+
b100 (
1%
1*
b111 "
#1150
0'
1+
0%
0.
0&
11
04
b101 (
0*
0-
00
13
b1000 "
#1155
1.
0+
b110 (
1%
1*
b1001 "
#1160
04
11
0'
1+
0%
1.
b111 (
0&
0*
1-
b1010 "
#1165
14
01
1'
0.
1&
0+
b1000 (
1%
1*
b1011 "
#1170
1+
0%
0.
0&
01
b1001 (
0*
0-
10
b1100 "
#1175
1.
0+
b1010 (
1%
1*
b1101 "
#1180
01
1+
0%
1.
b1011 (
0&
0*
1-
b1110 "
#1195
0$
11
0'
14
0+
b1110 (
0-
00
03
0)
1,
b0 "
b1110 !
#1200
1+
b1111 (
1*
b1 "
#1205
04
1$
01
1'
0+
0.
b0 (
1&
0*
1-
b10 "
#1210
1+
b1 (
1*
b11 "
#1215
0+
1.
0&
01
b10 (
0*
0-
10
b100 "
#1220
1+
b11 (
1*
b101 "
#1225
11
0+
0.
b100 (
1&
0*
1-
b110 "
#1230
1+
b101 (
1*
b111 "
#1235
0'
0+
1.
0&
11
04
b110 (
0*
0-
00
13
b1000 "
#1240
1+
b111 (
1*
b1001 "
#1245
14
01
1'
0+
0.
b1000 (
1&
0*
1-
b1010 "
#1250
1+
b1001 (
1*
b1011 "
#1255
0+
1.
0&
01
b1010 (
0*
0-
10
b1100 "
#1260
1+
b1011 (
1*
b1101 "
#1265
11
0+
0.
b1100 (
1&
0*
1-
b1110 "
